kyopro_utils/__init__.py
kyopro_utils/distance.py
kyopro_utils/output.py
kyopro_utils/standardinput.py
kyopro_utils/utils.py
kyopro_utils-1.0.dist-info/LICENSE
kyopro_utils-1.0.dist-info/METADATA
kyopro_utils-1.0.dist-info/WHEEL
kyopro_utils-1.0.dist-info/top_level.txt
kyopro_utils-1.0.dist-info/RECORD
