Metadata-Version: 2.1
Name: kyopro-utils
Version: 1.0
Summary: 競プロで何かと使う関数を作ってみました !Atcoderなどでは使えません 
Author: hidehic0
License: MIT
License-File: LICENSE
